pymodaq_plugins_hamamatsu/__init__.py
pymodaq_plugins_hamamatsu/utils.py
pymodaq_plugins_hamamatsu/app/__init__.py
pymodaq_plugins_hamamatsu/app/custom_app_template.py
pymodaq_plugins_hamamatsu/daq_move_plugins/__init__.py
pymodaq_plugins_hamamatsu/daq_viewer_plugins/__init__.py
pymodaq_plugins_hamamatsu/daq_viewer_plugins/plugins_1D/__init__.py
pymodaq_plugins_hamamatsu/daq_viewer_plugins/plugins_1D/daq_1Dviewer_MiniSpectro.py
pymodaq_plugins_hamamatsu/daq_viewer_plugins/plugins_2D/__init__.py
pymodaq_plugins_hamamatsu/daq_viewer_plugins/plugins_2D/daq_2Dviewer_Hamamatsu.py
pymodaq_plugins_hamamatsu/hardware/__init__.py
pymodaq_plugins_hamamatsu/hardware/minispectro.py
pymodaq_plugins_hamamatsu/resources/VERSION
pymodaq_plugins_hamamatsu/resources/__init__.py
pymodaq_plugins_hamamatsu/resources/config_template.toml
pymodaq_plugins_hamamatsu-0.3.0.dist-info/LICENSE
pymodaq_plugins_hamamatsu-0.3.0.dist-info/METADATA
pymodaq_plugins_hamamatsu-0.3.0.dist-info/WHEEL
pymodaq_plugins_hamamatsu-0.3.0.dist-info/entry_points.txt
pymodaq_plugins_hamamatsu-0.3.0.dist-info/top_level.txt
pymodaq_plugins_hamamatsu-0.3.0.dist-info/RECORD
