Metadata-Version: 2.1
Name: pymodaq-plugins-hamamatsu
Version: 0.3.0
Summary: Plugin for Hamamatsu instuments including DCAM-API based cameras and USB mini-spectrometers
Home-page: https://github.com/Attolab/pymodaq_plugins_hamamatsu
Author: Romain Géneaux
Author-email: romain.geneaux@cea.fr
License: MIT
Classifier: Programming Language :: Python :: 3
Classifier: Development Status :: 5 - Production/Stable
Classifier: Environment :: Other Environment
Classifier: Intended Audience :: Science/Research
Classifier: Topic :: Scientific/Engineering :: Human Machine Interfaces
Classifier: Topic :: Scientific/Engineering :: Visualization
Classifier: License :: OSI Approved :: MIT License
Classifier: Operating System :: OS Independent
Classifier: Topic :: Software Development :: Libraries :: Python Modules
Classifier: Topic :: Software Development :: User Interfaces
License-File: LICENSE
Requires-Dist: toml
Requires-Dist: numpy
Requires-Dist: pymodaq
Requires-Dist: pylablib
Requires-Dist: pythonnet
